udio_wrapper/__init__.py
udio_wrapper-0.0.3.dist-info/LICENSE
udio_wrapper-0.0.3.dist-info/METADATA
udio_wrapper-0.0.3.dist-info/WHEEL
udio_wrapper-0.0.3.dist-info/top_level.txt
udio_wrapper-0.0.3.dist-info/RECORD
