Metadata-Version: 2.1
Name: udio-wrapper
Version: 0.0.3
Summary: Generates songs using the Udio API using textual prompts.
Home-page: https://github.com/flowese/UdioWrapper
Author: Flowese
Author-email: flowese@gmail.com
Keywords: audio,music,generation,API,AI,Udio
Classifier: Programming Language :: Python :: 3
Classifier: License :: OSI Approved :: MIT License
Classifier: Operating System :: OS Independent
Requires-Python: >=3.8
License-File: LICENSE
Requires-Dist: requests==2.31.0
